uldlib/__init__.py
uldlib/captcha.py
uldlib/cmd.py
uldlib/const.py
uldlib/downloader.py
uldlib/frontend.py
uldlib/linkcache.py
uldlib/model.tflite
uldlib/page.py
uldlib/part.py
uldlib/segfile.py
uldlib/torrunner.py
uldlib/utils.py
uld-3.1.8.dist-info/AUTHORS.md
uld-3.1.8.dist-info/LICENSE.txt
uld-3.1.8.dist-info/METADATA
uld-3.1.8.dist-info/WHEEL
uld-3.1.8.dist-info/entry_points.txt
uld-3.1.8.dist-info/top_level.txt
uld-3.1.8.dist-info/RECORD
