Metadata-Version: 2.1
Name: uld
Version: 3.1.8
Summary: Uloz.to quick multiple sessions downloader. This is fork of original https://github.com/setnicka/ulozto-downloader for pre-release pull-requests
Home-page: https://github.com/setnicka/ulozto-downloader
Author: Jiří Setnička, vladodriver and many others..
Author-email: setnicka@seznam.cz
License: MIT
Classifier: License :: OSI Approved :: MIT License
Classifier: Programming Language :: Python :: 3
Requires-Python: >=3.7
License-File: LICENSE.txt
License-File: AUTHORS.md
Requires-Dist: requests
Requires-Dist: Pillow
Requires-Dist: ansicolors
Requires-Dist: numpy
Requires-Dist: pysocks
Requires-Dist: stem
Requires-Dist: appdirs
Provides-Extra: auto-captcha
Requires-Dist: tensorflow ; (platform_system == "Windows") and extra == 'auto-captcha'
